{"binner_md5":"unknown","entry_price":74356.0,"entry_ts_ms":1776259712092,"event_type":"signal_closed","exit_price":74382.1206,"exit_reason":"tp","exit_ts_ms":1776263108340,"gate_states_at_trigger":{},"hit_3bps":true,"hold_ms":3396248,"mae_bps":76.92721501963527,"market_context":{},"mfe_bps":5.514013663994835,"net_bps_after_fees":0.5129108612613291,"realized_bps":3.512910861261329,"schema_version":1,"side":"LONG","signal_id":"S4-180_1776259712092","strategy_id":"S4-180","strategy_version":"unknown","virginia_worker_version":"2026.04.13-a","written_at_ms":1776263108475}