{"binner_md5":"unknown","entry_price":74318.0,"entry_ts_ms":1776256871185,"event_type":"signal_closed","exit_price":74372.1226,"exit_reason":"tp","exit_ts_ms":1776259598478,"gate_states_at_trigger":{},"hit_3bps":true,"hold_ms":2727293,"mae_bps":23.951128932425526,"market_context":{},"mfe_bps":9.28442638391776,"net_bps_after_fees":4.282569498641301,"realized_bps":7.282569498641301,"schema_version":1,"side":"LONG","signal_id":"S4-182_1776256871185","strategy_id":"S4-182","strategy_version":"unknown","virginia_worker_version":"2026.04.13-a","written_at_ms":1776259598565}