{"binner_md5":"unknown","entry_price":74603.0,"entry_ts_ms":1776280509988,"event_type":"signal_closed","exit_price":74648.0674,"exit_reason":"tp","exit_ts_ms":1776280748532,"gate_states_at_trigger":{},"hit_3bps":true,"hold_ms":238544,"mae_bps":8.310657748347921,"market_context":{},"mfe_bps":8.042572014530247,"net_bps_after_fees":3.0409635001273285,"realized_bps":6.0409635001273285,"schema_version":1,"side":"LONG","signal_id":"S4-185_1776280509988","strategy_id":"S4-185","strategy_version":"unknown","virginia_worker_version":"2026.04.13-a","written_at_ms":1776280748640}