{"binner_md5":"unknown","entry_price":74606.0,"entry_ts_ms":1776280812478,"event_type":"signal_closed","exit_price":74652.0666,"exit_reason":"tp","exit_ts_ms":1776281317923,"gate_states_at_trigger":{},"hit_3bps":true,"hold_ms":505445,"mae_bps":11.52722301155403,"market_context":{},"mfe_bps":8.176286089590649,"net_bps_after_fees":3.1746508323734774,"realized_bps":6.1746508323734774,"schema_version":1,"side":"LONG","signal_id":"S4-193_1776280812478","strategy_id":"S4-193","strategy_version":"unknown","virginia_worker_version":"2026.04.13-a","written_at_ms":1776281318061}