{"binner_md5":"unknown","entry_price":73824.0,"entry_ts_ms":1776268913208,"event_type":"signal_closed","exit_price":73891.8258,"exit_reason":"tp","exit_ts_ms":1776268966795,"gate_states_at_trigger":{},"hit_3bps":true,"hold_ms":53586,"mae_bps":0.0,"market_context":{},"mfe_bps":12.191157347204163,"net_bps_after_fees":6.18750000000081,"realized_bps":9.18750000000081,"schema_version":1,"side":"LONG","signal_id":"S4-204_1776268913208","strategy_id":"S4-204","strategy_version":"unknown","virginia_worker_version":"2026.04.13-a","written_at_ms":1776268966907}