{"binner_md5":"unknown","entry_price":74213.0,"entry_ts_ms":1776198142731,"event_type":"signal_closed","exit_price":74239.1492,"exit_reason":"tp","exit_ts_ms":1776204640437,"gate_states_at_trigger":{},"hit_3bps":true,"hold_ms":6497705,"mae_bps":43.119130071550806,"market_context":{},"mfe_bps":5.524638540417446,"net_bps_after_fees":0.5235336127093415,"realized_bps":3.5235336127093415,"schema_version":1,"side":"LONG","signal_id":"S4-188_1776198142731","strategy_id":"S4-188","strategy_version":"unknown","virginia_worker_version":"2026.04.13-a","written_at_ms":1776204640532}